Nova_Tools/NovaTools.py
Nova_Tools/__init__.py
Nova_Tools-5.10.dist-info/LICENSE
Nova_Tools-5.10.dist-info/METADATA
Nova_Tools-5.10.dist-info/WHEEL
Nova_Tools-5.10.dist-info/top_level.txt
Nova_Tools-5.10.dist-info/RECORD
