Metadata-Version: 2.1
Name: Nova-Tools
Version: 5.10
Summary: For developers
Home-page: https://github.com/NovaTools4/Nova_Tools
Author: The Jordan Ghost
Author-email: Novayou0@gmail.com
Project-URL: Bug Tracker, https://github.com/pypa/sampleproject/issues
Keywords: Nova_Tools
Classifier: Development Status :: 1 - Planning
Classifier: Intended Audience :: Developers
Classifier: Programming Language :: Python :: 3
Classifier: Operating System :: Unix
Classifier: Operating System :: MacOS :: MacOS X
Classifier: Operating System :: Microsoft :: Windows
License-File: LICENSE
Requires-Dist: requests
Requires-Dist: geocoder
Requires-Dist: user-agent
Requires-Dist: pyfiglet
